cleedpy/config.py
cleedpy/version.py
cleedpy/preprocess.py
cleedpy/libmat.dylib
cleedpy/__init__.py
cleedpy/rfactor.py
cleedpy/search.py
cleedpy/libcleed.dylib
cleedpy/interface/matrix.py
cleedpy/interface/cleed.py
cleedpy/interface/__init__.py
cleedpy/cli/__init__.py
cleedpy/cli/rfactor.py
cleedpy/cli/validate_parameters.py
cleedpy/cli/generate_schema.py
cleedpy/cli/leed.py
cleedpy/cli/search.py
cleedpy/cleed/Makefile.original
cleedpy/cleed/CMakeLists.txt
cleedpy/cleed/include/leed_def.h
cleedpy/cleed/include/mat_lapack.h
cleedpy/cleed/include/qm.h
cleedpy/cleed/include/dla.h
cleedpy/cleed/include/mat.h
cleedpy/cleed/include/mat_def.h
cleedpy/cleed/include/cpl.h
cleedpy/cleed/include/cpl_func.h
cleedpy/cleed/include/mat_func.h
cleedpy/cleed/include/leed_ver_sym.h
cleedpy/cleed/include/real.h
cleedpy/cleed/include/leed.h
cleedpy/cleed/include/leed_func.h
cleedpy/cleed/include/qm_func.h
cleedpy/cleed/include/gh_stddef.h
cleedpy/cleed/include/leed_ver_temp.h
cleedpy/cleed/include/cblas_f77.h
cleedpy/cleed/include/mat_blas.h
cleedpy/cleed/include/cpl_macr.h
cleedpy/cleed/src/lpcmkms.c
cleedpy/cleed/src/lmslsumii.c
cleedpy/cleed/src/linpphasend.c
cleedpy/cleed/src/lld2n.c
cleedpy/cleed/src/linpmatlm.c
cleedpy/cleed/src/lmspartinv.c
cleedpy/cleed/src/leed.c
cleedpy/cleed/src/qmylm.c
cleedpy/cleed/src/lld2lay.c
cleedpy/cleed/src/CMakeLists.txt
cleedpy/cleed/src/lbmset.c
cleedpy/cleed/src/loutbmlist.c
cleedpy/cleed/src/lpctemtl.c
cleedpy/cleed/src/lmsbravl.c
cleedpy/cleed/src/lmscomplnd.c
cleedpy/cleed/src/lpcmktlnd.c
cleedpy/cleed/src/lmslsumij.c
cleedpy/cleed/src/lpcmktl.c
cleedpy/cleed/src/lmsbravlnd.c
cleedpy/cleed/src/linpovllayer.c
cleedpy/cleed/src/lpccumtl.c
cleedpy/cleed/src/cribasfun.c
cleedpy/cleed/src/lldpotstep0.c
cleedpy/cleed/src/lld2layrpm.c
cleedpy/cleed/src/lpcupdate.c
cleedpy/cleed/src/linprdpar.c
cleedpy/cleed/src/linpbullayer.c
cleedpy/cleed/src/lmsltok.c
cleedpy-0.1.6.dist-info/RECORD
cleedpy-0.1.6.dist-info/WHEEL
cleedpy-0.1.6.dist-info/entry_points.txt
cleedpy-0.1.6.dist-info/METADATA
cleedpy-0.1.6.dist-info/licenses/LICENSE
