Metadata-Version: 2.2
Name: cleedpy
Version: 0.1.6
License: MIT License
Classifier: Development Status :: 2 - Pre-Alpha
Classifier: Intended Audience :: Science/Research
Classifier: License :: OSI Approved :: MIT License
Classifier: Programming Language :: C
Classifier: Programming Language :: Python
Classifier: Programming Language :: Python :: 3
Classifier: Programming Language :: Python :: 3.10
Classifier: Programming Language :: Python :: 3.11
Classifier: Programming Language :: Python :: 3.12
Requires-Python: >=3.10
Requires-Dist: ase
Requires-Dist: click
Requires-Dist: jinja2
Requires-Dist: matplotlib
Requires-Dist: numpy
Requires-Dist: pydantic
Requires-Dist: pyyaml
Requires-Dist: scipy
Requires-Dist: typer
Provides-Extra: dev
Requires-Dist: bumpver==2023.1129; extra == "dev"
Requires-Dist: pre-commit==4.3.0; extra == "dev"
Requires-Dist: pytest==7.4.4; extra == "dev"
Requires-Dist: pytest-cov==4.1.0; extra == "dev"
